{
  "public_metrics": {
    "retweet_count": 1,
    "reply_count": 1,
    "like_count": 0,
    "quote_count": 0,
    "bookmark_count": 0,
    "impression_count": 0
  },
  "edit_history_tweet_ids": [
    "285639445800173568"
  ],
  "entities": {
    "mentions": [
      {
        "start": 0,
        "end": 11,
        "username": "Enalrachid",
        "id": "196127798"
      },
      {
        "start": 12,
        "end": 24,
        "username": "fadyadel007",
        "id": "266323755"
      },
      {
        "start": 25,
        "end": 36,
        "username": "omeshayeck",
        "id": "465918777"
      },
      {
        "start": 37,
        "end": 45,
        "username": "Ado0o0o",
        "id": "40636627"
      },
      {
        "start": 46,
        "end": 60,
        "username": "oneworld4ever",
        "id": "599051960"
      },
      {
        "start": 61,
        "end": 75,
        "username": "husseinmoussa",
        "id": "255409293"
      },
      {
        "start": 76,
        "end": 84,
        "username": "jo_msk1",
        "id": "375020472"
      },
      {
        "start": 85,
        "end": 97,
        "username": "barsoumramy",
        "id": "254267633"
      }
    ]
  },
  "text": "@Enalrachid @fadyadel007 @omeshayeck @Ado0o0o @oneworld4ever @husseinmoussa @jo_msk1 @barsoumramy\nكل سنة وانتم طيبين جميعا و اللى جاى احلى",
  "author_id": "488569242",
  "referenced_tweets": [
    {
      "type": "replied_to",
      "id": "285556238178201601"
    }
  ],
  "id": "285639445800173568",
  "in_reply_to_user_id": "196127798",
  "created_at": "2012-12-31T06:52:05.000Z",
  "_author": {
    "id": "488569242",
    "name": "ahmed kamal",
    "username": "84Hamada"
  },
  "_collected_at": "2026-04-13T23:13:25.002Z",
  "_stream": "mentions"
}