{
  "created_at": "2026-04-13T21:08:19.000Z",
  "author_id": "1068465812",
  "text": "I built an MCP server on top of my trading system this year. Essentially an API layer that lets external AI tools interact with the whole thing. An AI assistant can now pull active trades, check session stats, read preparation context, even queue up certain actions.\n\nI went back",
  "edit_history_tweet_ids": [
    "2043798461598883962"
  ],
  "id": "2043798461598883962",
  "public_metrics": {
    "retweet_count": 0,
    "reply_count": 1,
    "like_count": 0,
    "quote_count": 0,
    "bookmark_count": 0,
    "impression_count": 24
  },
  "_author": {
    "id": "1068465812",
    "name": "Simeon Vanov",
    "username": "simo_vanov"
  },
  "_collected_at": "2026-04-13T23:13:26.844Z",
  "_stream": "search_6",
  "_search_query": "\"personal AI\" OR \"AI assistant\""
}