{
  "created_at": "2026-04-12T12:31:17.000Z",
  "author_id": "3195951780",
  "text": "you don't need 5 different AI agents that can't talk to each other.\n\nyou need agents connected through open standards.\nenter Model Context Protocol (MCP).\n\nhere's what changed:\nbefore: sales agent ≠ finance agent. they live in different worlds. you're the translator. friction",
  "public_metrics": {
    "retweet_count": 0,
    "reply_count": 0,
    "like_count": 1,
    "quote_count": 0,
    "bookmark_count": 0,
    "impression_count": 21
  },
  "edit_history_tweet_ids": [
    "2043305954553581583"
  ],
  "id": "2043305954553581583",
  "_author": {
    "id": "3195951780",
    "name": "aaraf armin",
    "username": "privrafi"
  },
  "_collected_at": "2026-04-13T23:13:27.346Z",
  "_stream": "search_7",
  "_search_query": "\"MCP protocol\" OR \"model context protocol\""
}